.coveragerc
.dockerignore
.gitignore
.mailmap
.rsyncexclude
.testr.conf
CODE_OF_CONDUCT.md
COPYING.txt
Cargo.lock
Cargo.toml
MANIFEST.in
README.md
pyproject.toml
setup.py
.github/CODEOWNERS
.github/dependabot.yaml
.github/workflows/pythonpackage.yml
.github/workflows/wheels.yaml
crates/graph/Cargo.toml
crates/graph-py/Cargo.toml
crates/graph-py/src/lib.rs
crates/graph/src/lib.rs
crates/graph/src/parents_provider.rs
crates/graph/src/test.rs
crates/graph/src/tsort.rs
vcsgraph/.gitignore
vcsgraph/__init__.py
vcsgraph/errors.py
vcsgraph/graph.py
vcsgraph/known_graph.py
vcsgraph/py.typed
vcsgraph/tsort.py
vcsgraph.egg-info/PKG-INFO
vcsgraph.egg-info/SOURCES.txt
vcsgraph.egg-info/dependency_links.txt
vcsgraph.egg-info/requires.txt
vcsgraph.egg-info/top_level.txt
vcsgraph/tests/__init__.py
vcsgraph/tests/test_graph.py
vcsgraph/tests/test_known_graph.py
vcsgraph/tests/test_tsort.py