Metadata-Version: 2.4
Name: vcsgraph
Version: 0.1.0
Summary: Graph algorithms for version control systems
Requires-Python: >=3.9
License-File: COPYING.txt
Provides-Extra: dev
Requires-Dist: mypy==1.17.1; extra == "dev"
Requires-Dist: ruff==0.12.1; extra == "dev"
Dynamic: license-file
